{
  "id": "halbert_copywriting_method_part_iii",
  "title": "The Halbert Copywriting Method Part III: The Simple Fast & Easy Editing Formula That Forces Buyers To Read Every Word Of Your Ads",
  "author": "Bond Halbert",
  "year": 2016,
  "tags": ["copywriting", "editing", "direct_response", "persuasion", "psychology", "bond_halbert"],
  "description": "Một hướng dẫn thực chiến về quy trình chỉnh sửa (editing) trong copywriting nhằm tối ưu hóa sự mượt mà của văn bản, giữ chân người đọc và tiêm vào các yếu tố tâm lý ẩn để gia tăng tỷ lệ chuyển đổi."
}
